limelight.py
limelightresults.py
limelightlib_python-0.9.6.dist-info/METADATA
limelightlib_python-0.9.6.dist-info/WHEEL
limelightlib_python-0.9.6.dist-info/top_level.txt
limelightlib_python-0.9.6.dist-info/RECORD
