Metadata-Version: 2.1
Name: limelightlib-python
Version: 0.9.6
Summary: Built to interface with any Limelight Smart Camera
Home-page: https://limelightvision.io
Author: Brandon Hjelstrom
Author-email: brandon@limelightvision.io
Classifier: Programming Language :: Python :: 3
Classifier: License :: OSI Approved :: MIT License
Classifier: Operating System :: OS Independent
Requires-Python: >=3.6
Requires-Dist: websocket-client >=1.5
Requires-Dist: requests
Requires-Dist: ifaddr
